open_cobol_ide/app.py
open_cobol_ide/__init__.py
open_cobol_ide/compilers.py
open_cobol_ide/linter.py
open_cobol_ide/system.py
open_cobol_ide/settings.py
open_cobol_ide/logger.py
open_cobol_ide/main.py
open_cobol_ide/enums.py
open_cobol_ide/memoize.py
open_cobol_ide/controllers/base.py
open_cobol_ide/controllers/file.py
open_cobol_ide/controllers/edit.py
open_cobol_ide/controllers/view.py
open_cobol_ide/controllers/__init__.py
open_cobol_ide/controllers/help.py
open_cobol_ide/controllers/home.py
open_cobol_ide/controllers/cobol.py
open_cobol_ide/view/__init__.py
open_cobol_ide/view/widgets.py
open_cobol_ide/view/main_window.py
open_cobol_ide/view/forms/dlg_file_type_ui.py
open_cobol_ide/view/forms/ide_ui.py
open_cobol_ide/view/forms/__init__.py
open_cobol_ide/view/forms/dlg_report_bug_ui.py
open_cobol_ide/view/forms/dlg_check_compiler_ui.py
open_cobol_ide/view/forms/dlg_preferences_ui.py
open_cobol_ide/view/forms/dlg_about_ui.py
open_cobol_ide/view/forms/ide_rc.py
open_cobol_ide/view/editors/generic.py
open_cobol_ide/view/editors/__init__.py
open_cobol_ide/view/editors/text.py
open_cobol_ide/view/editors/cobol.py
open_cobol_ide/view/dialogs/preferences.py
open_cobol_ide/view/dialogs/check_compiler.py
open_cobol_ide/view/dialogs/__init__.py
open_cobol_ide/view/dialogs/report_bug.py
open_cobol_ide/view/dialogs/new_file.py
open_cobol_ide/view/dialogs/about.py
OpenCobolIDE-4.6.2.dist-info/RECORD
OpenCobolIDE-4.6.2.dist-info/DESCRIPTION.rst
OpenCobolIDE-4.6.2.dist-info/WHEEL
OpenCobolIDE-4.6.2.dist-info/entry_points.txt
OpenCobolIDE-4.6.2.dist-info/METADATA
OpenCobolIDE-4.6.2.dist-info/metadata.json
OpenCobolIDE-4.6.2.dist-info/top_level.txt
OpenCobolIDE-4.6.2.data/data/share/pixmaps/OpenCobolIDE.png
OpenCobolIDE-4.6.2.data/data/share/applications/OpenCobolIDE.desktop
