Metadata-Version: 2.0
Name: OpenCobolIDE
Version: 4.6.2
Summary: A simple COBOL IDE
Home-page: https://github.com/OpenCobolIDE/OpenCobolIDE
Author: Colin Duquesnoy
Author-email: colin.duquesnoy@gmail.com
License: GPL v3
Keywords: Cobol; OpenCobol; IDE
Platform: UNKNOWN
Classifier: Development Status :: 5 - Production/Stable
Classifier: Environment :: X11 Applications :: Qt
Classifier: Environment :: Win32 (MS Windows)
Classifier: Intended Audience :: Developers
Classifier: License :: OSI Approved :: GNU General Public License v3 or later (GPLv3+)
Classifier: Operating System :: Microsoft :: Windows
Classifier: Operating System :: POSIX :: Linux
Classifier: Programming Language :: Python :: 3.2
Classifier: Programming Language :: Python :: 3.3
Classifier: Programming Language :: Python :: 3.4
Classifier: Topic :: Text Editors :: Integrated Development Environments (IDE)
Requires-Dist: pygments (>=1.6)
Requires-Dist: pyqode.core (>=2.5.0)
Requires-Dist: pyqode.cobol (>=2.5.0)
Requires-Dist: pyqode.qt (>=2.5.0)
Requires-Dist: qdarkstyle (>=1.11)
